xdf/__init__.py
xdf/_abc.py
xdf/util/cache.py
xdf/util/date_time copy.py
xdf/util/date_time.py
xdf/util/decor.py
xdf/util/eval_metrics.py
xdf/util/pkl.py
xdf/util/aws/__init__.py
xdf/util/aws/rds.py
xdf/util/aws/ec2/instance_types.py
xdf/util/data_backend/__init__.py
xdf/util/data_backend/yarn/alloc.py
XDF-23.6.14.0.dist-info/LICENSE
XDF-23.6.14.0.dist-info/METADATA
XDF-23.6.14.0.dist-info/WHEEL
XDF-23.6.14.0.dist-info/top_level.txt
XDF-23.6.14.0.dist-info/zip-safe
XDF-23.6.14.0.dist-info/RECORD
