Metadata-Version: 2.1
Name: XDF
Version: 23.6.14.0
Summary: Data Frames / Data Feeders with high-level abstractions for key tasks in AI applications
Author-email: "STEAM for Vietnam Foundation: AI, IoT & Robotics Educational Initiative" <Edu.AI@STEAMforVietNam.org>
Maintainer-email: "STEAM for Vietnam Foundation: AI, IoT & Robotics Educational Initiative" <Edu.AI@STEAMforVietNam.org>
License: MIT License
Project-URL: Homepage, https://GitHub.com/Djaizz/XDF
Project-URL: Repository, https://GitHub.com/Djaizz/XDF
Project-URL: GitHub, https://GitHub.com/Djaizz/XDF
Project-URL: Documentation, https://Djaizz.GitHub.io/XDF
Keywords: data frame,data feeder,Artificial Intelligence,A.I.,AI,application,app
Classifier: Development Status :: 3 - Alpha
Classifier: Environment :: MacOS X
Classifier: Environment :: Win32 (MS Windows)
Classifier: Framework :: Dash
Classifier: Framework :: Django
Classifier: Framework :: Django :: 4.0
Classifier: Framework :: IPython
Classifier: Framework :: Jupyter
Classifier: Framework :: Jupyter :: JupyterLab
Classifier: Framework :: Jupyter :: JupyterLab :: 4
Classifier: Framework :: Kedro
Classifier: Framework :: Matplotlib
Classifier: Intended Audience :: Developers
Classifier: Intended Audience :: Education
Classifier: Intended Audience :: Financial and Insurance Industry
Classifier: Intended Audience :: Healthcare Industry
Classifier: Intended Audience :: Information Technology
Classifier: Intended Audience :: Legal Industry
Classifier: Intended Audience :: Manufacturing
Classifier: Intended Audience :: Science/Research
Classifier: Intended Audience :: System Administrators
Classifier: Intended Audience :: Telecommunications Industry
Classifier: Operating System :: MacOS
Classifier: Operating System :: MacOS :: MacOS X
Classifier: Operating System :: Microsoft
Classifier: Operating System :: Microsoft :: Windows
Classifier: Operating System :: Microsoft :: Windows :: Windows 7
Classifier: Operating System :: Microsoft :: Windows :: Windows 8
Classifier: Operating System :: Microsoft :: Windows :: Windows 8.1
Classifier: Operating System :: Microsoft :: Windows :: Windows 10
Classifier: Operating System :: OS Independent
Classifier: Operating System :: Other OS
Classifier: Operating System :: POSIX
Classifier: Operating System :: POSIX :: Linux
Classifier: Programming Language :: Python
Classifier: Programming Language :: Python :: 3
Classifier: Programming Language :: Python :: 3.8
Classifier: Programming Language :: Python :: 3.9
Classifier: Programming Language :: Python :: 3.10
Classifier: Programming Language :: Python :: 3.11
Classifier: Topic :: Education
Classifier: Topic :: Home Automation
Classifier: Topic :: Scientific/Engineering
Classifier: Topic :: Scientific/Engineering :: Artificial Intelligence
Classifier: Topic :: Scientific/Engineering :: Astronomy
Classifier: Topic :: Scientific/Engineering :: Atmospheric Science
Classifier: Topic :: Scientific/Engineering :: Bio-Informatics
Classifier: Topic :: Scientific/Engineering :: Chemistry
Classifier: Topic :: Scientific/Engineering :: GIS
Classifier: Topic :: Scientific/Engineering :: Human Machine Interfaces
Classifier: Topic :: Scientific/Engineering :: Hydrology
Classifier: Topic :: Scientific/Engineering :: Image Processing
Classifier: Topic :: Scientific/Engineering :: Image Recognition
Classifier: Topic :: Scientific/Engineering :: Information Analysis
Classifier: Topic :: Scientific/Engineering :: Mathematics
Classifier: Topic :: Scientific/Engineering :: Medical Science Apps.
Classifier: Topic :: Scientific/Engineering :: Physics
Classifier: Topic :: Scientific/Engineering :: Visualization
Classifier: Topic :: Software Development
Classifier: Topic :: Software Development :: Libraries
Classifier: Topic :: Software Development :: Libraries :: Application Frameworks
Classifier: Topic :: Software Development :: Libraries :: Python Modules
Classifier: Topic :: Software Development :: User Interfaces
Classifier: Topic :: Software Development :: Widget Sets
Requires-Python: >=3.11
License-File: LICENSE
Provides-Extra: build
Requires-Dist: Build (>=0.10.0) ; extra == 'build'
Provides-Extra: dev
Requires-Dist: Commitizen (>=3.3.0) ; extra == 'dev'
Requires-Dist: Pre-Commit (>=3.3.2) ; extra == 'dev'
Provides-Extra: doc
Requires-Dist: Sphinx (>=7.0.1) ; extra == 'doc'
Requires-Dist: Sphinx-AutoBuild (>=2021.3.14) ; extra == 'doc'
Requires-Dist: SphinxContrib-JSMath (>=1.0.1) ; extra == 'doc'
Requires-Dist: CommonMark (>=0.9.1) ; extra == 'doc'
Requires-Dist: ReCommonMark (>=0.7.1) ; extra == 'doc'
Provides-Extra: lint
Requires-Dist: Bandit (>=1.7.5) ; extra == 'lint'
Requires-Dist: Flake8 (>=6.0.0) ; extra == 'lint'
Requires-Dist: MyPy (>=1.3.0) ; extra == 'lint'
Requires-Dist: PyCodeStyle (>=2.10.0) ; extra == 'lint'
Requires-Dist: PyDocStyle (>=6.3.0) ; extra == 'lint'
Requires-Dist: PyLama (>=8.4.1) ; extra == 'lint'
Requires-Dist: PyLint (>=2.17.4) ; extra == 'lint'
Provides-Extra: publish
Requires-Dist: Twine (>=4.0.2) ; extra == 'publish'
Provides-Extra: test
Requires-Dist: Nose (>=1.3.7) ; extra == 'test'
Requires-Dist: Nose2 (>=0.13.0) ; extra == 'test'
Requires-Dist: PyTest (>=7.3.2) ; extra == 'test'
Requires-Dist: PyTest-Cov (>=4.1.0) ; extra == 'test'
Requires-Dist: UnitTest2 (>=1.1.0) ; extra == 'test'
